Metadata-Version: 2.1
Name: SimpleEngine
Version: 0.3
Summary: A simple game engine
Home-page: 
Author: Gust Schadron
Author-email: gustscd@gmail.com
License: MIT
Keywords: game
Classifier: Development Status :: 5 - Production/Stable
Classifier: Intended Audience :: Education
Classifier: Operating System :: Microsoft :: Windows :: Windows 10
Classifier: License :: OSI Approved :: MIT License
Classifier: Programming Language :: Python :: 3
